ai_zap/1_text_processor.py
ai_zap/2_file_io.py
ai_zap/3_phone_app.py
ai_zap/4_bubble_sort.py
ai_zap/5_student_class.py
ai_zap/__init__.py
ai_zap/otv.txt
ai_zap-1.0.6.dist-info/METADATA
ai_zap-1.0.6.dist-info/WHEEL
ai_zap-1.0.6.dist-info/top_level.txt
ai_zap-1.0.6.dist-info/RECORD
