Metadata-Version: 2.4
Name: ai-zap
Version: 1.0.6
Summary: Библиотека для работы с ИИ и практическими заданиями
Home-page: https://github.com/yourusername/ai-zap
Author: Danila
Author-email: your.email@example.com
Classifier: Programming Language :: Python :: 3
Classifier: License :: OSI Approved :: MIT License
Classifier: Operating System :: OS Independent
Requires-Python: >=3.6
Requires-Dist: openai>=1.0.0
Dynamic: author
Dynamic: author-email
Dynamic: classifier
Dynamic: description
Dynamic: description-content-type
Dynamic: home-page
Dynamic: requires-dist
Dynamic: requires-python
Dynamic: summary
